gxkit_datalab/__init__.py
gxkit_datalab/exception.py
gxkit_datalab/py.typed
gxkit_datalab/align/__init__.py
gxkit_datalab/align/time_align.py
gxkit_datalab/detect/__init__.py
gxkit_datalab/detect/dl_detect.py
gxkit_datalab/detect/ml_detect.py
gxkit_datalab/detect/physical_detect.py
gxkit_datalab/detect/stat_detect.py
gxkit_datalab/encode/__init__.py
gxkit_datalab/encode/bitmask.py
gxkit_datalab/interp/__init__.py
gxkit_datalab/interp/ml_interpolate.py
gxkit_datalab/interp/stat_interpolate.py
gxkit_datalab/mark/__init__.py
gxkit_datalab/mark/daytime.py
gxkit_datalab/mark/missing.py
gxkit_datalab/transform/__init__.py
gxkit_datalab/utils/__init__.py
gxkit_datalab/utils/check.py
gxkit_datalab/utils/convert.py
gxkit_datalab/utils/normalize.py
gxkit_datalab-0.1.0.post4.dist-info/licenses/LICENSE
gxkit_datalab-0.1.0.post4.dist-info/METADATA
gxkit_datalab-0.1.0.post4.dist-info/WHEEL
gxkit_datalab-0.1.0.post4.dist-info/top_level.txt
gxkit_datalab-0.1.0.post4.dist-info/RECORD
