Metadata-Version: 2.4
Name: gxkit-datalab
Version: 0.1.0.post4
Summary: Gx Company Development Toolkit - DataLab Module
Author-email: Shaojiayi <shaojy@sunburst.com.cn>
License: Apache-2.0
Requires-Python: >=3.8
License-File: LICENSE
Requires-Dist: pandas
Requires-Dist: scipy
Dynamic: license-file
